st_common/__init__.py
st_common/ccookies.py
st_common/commonbase.py
st_common/dbmodule.py
st_common/emailmodule.py
st_common/famodule.py
st_common/msgreport.py
st_common/rpamodule.py
st_common/securemodule.py
st_common-1.4.8.dist-info/LICENSE
st_common-1.4.8.dist-info/METADATA
st_common-1.4.8.dist-info/WHEEL
st_common-1.4.8.dist-info/top_level.txt
st_common-1.4.8.dist-info/RECORD
