Metadata-Version: 2.1
Name: st-common
Version: 1.4.8
Summary: suitcase in st st_common module
Home-page: https://github.com/VinMing/common
Author: St
Author-email: st@gmail.com
License: ISC
Classifier: Development Status :: 5 - Production/Stable
Classifier: Intended Audience :: Developers
Classifier: Natural Language :: English
Classifier: License :: OSI Approved :: BSD License
Classifier: Programming Language :: Python
Classifier: Programming Language :: Python :: 3
Classifier: Programming Language :: Python :: 3.10
Classifier: Programming Language :: Python :: Implementation :: CPython
Classifier: Programming Language :: Python :: Implementation :: PyPy
Requires-Python: >=3.10
License-File: LICENSE
Requires-Dist: requests
Requires-Dist: SQLAlchemy
Requires-Dist: redis
Requires-Dist: pymongo
Requires-Dist: pandas
Requires-Dist: python-dotenv
Requires-Dist: pycryptodome
Requires-Dist: Pillow
Requires-Dist: paddlepaddle
Requires-Dist: paddleocr
